vsview/__init__.py
vsview/__main__.py
vsview/cli.py
vsview/logging.py
vsview/py.typed
vsview/api/__init__.py
vsview/api/_helpers.py
vsview/api/output.py
vsview/app/__init__.py
vsview/app/error.py
vsview/app/main.py
vsview/app/utils.py
vsview/app/outputs/__init__.py
vsview/app/outputs/audio.py
vsview/app/outputs/buffer.py
vsview/app/outputs/manager.py
vsview/app/outputs/packing.py
vsview/app/outputs/video.py
vsview/app/plugins/__init__.py
vsview/app/plugins/_interface.py
vsview/app/plugins/api.py
vsview/app/plugins/manager.py
vsview/app/plugins/specs.py
vsview/app/settings/__init__.py
vsview/app/settings/dialog.py
vsview/app/settings/enums.py
vsview/app/settings/manager.py
vsview/app/settings/models.py
vsview/app/settings/shortcuts.py
vsview/app/tools/frameprops/__init__.py
vsview/app/tools/frameprops/api.py
vsview/app/tools/frameprops/categories.py
vsview/app/tools/frameprops/formatters.py
vsview/app/tools/frameprops/plugin.py
vsview/app/tools/frameprops/specs.py
vsview/app/tools/frameprops/builtins/field.py
vsview/app/tools/frameprops/builtins/metrics.py
vsview/app/tools/frameprops/builtins/video.py
vsview/app/views/__init__.py
vsview/app/views/components.py
vsview/app/views/splitter.py
vsview/app/views/status.py
vsview/app/views/tab.py
vsview/app/views/timeline.py
vsview/app/views/video.py
vsview/app/workspace/__init__.py
vsview/app/workspace/base.py
vsview/app/workspace/file.py
vsview/app/workspace/loader.py
vsview/app/workspace/playback.py
vsview/app/workspace/quick_script.py
vsview/app/workspace/tab_manager.py
vsview/assets/__init__.py
vsview/assets/icon.png
vsview/assets/loading.png
vsview/assets/providers.py
vsview/assets/utils.py
vsview/assets/fonts/Cascadia_Mono/CascadiaMono-Italic-VariableFont_wght.ttf
vsview/assets/fonts/Cascadia_Mono/CascadiaMono-VariableFont_wght.ttf
vsview/assets/fonts/Cascadia_Mono/LICENSE.txt
vsview/assets/icons/LICENSES.md
vsview/assets/icons/lucide/arrow-left.svg
vsview/assets/icons/lucide/arrow-right.svg
vsview-0.1.0a1.dist-info/METADATA
vsview-0.1.0a1.dist-info/WHEEL
vsview-0.1.0a1.dist-info/entry_points.txt
vsview-0.1.0a1.dist-info/licenses/LICENSE
vsview-0.1.0a1.dist-info/RECORD
