Metadata-Version: 2.4
Name: vsview
Version: 0.1.0a1
Summary: The next-generation VapourSynth previewer
Project-URL: Source Code, https://github.com/Jaded-Encoding-Thaumaturgy/vs-view
Project-URL: Bug Tracker, https://github.com/Jaded-Encoding-Thaumaturgy/vs-view/issues
Project-URL: Contact, https://discord.gg/XTpc6Fa9eB
License:                       EUROPEAN UNION PUBLIC LICENCE v. 1.2
License-File: LICENSE
Classifier: Development Status :: 3 - Alpha
Classifier: License :: OSI Approved :: European Union Public Licence 1.2 (EUPL 1.2)
Classifier: Operating System :: OS Independent
Classifier: Programming Language :: Python :: 3
Classifier: Programming Language :: Python :: 3 :: Only
Classifier: Programming Language :: Python :: 3.12
Classifier: Programming Language :: Python :: 3.13
Classifier: Programming Language :: Python :: 3.14
Classifier: Topic :: Multimedia :: Graphics
Classifier: Typing :: Typed
Requires-Python: >=3.12
Requires-Dist: jetpytools>=2.2.2
Requires-Dist: pluggy>=1.6.0
Requires-Dist: pydantic>=2.0.0
Requires-Dist: pygments>=2.19.0
Requires-Dist: pyside6>=6.10.1
Requires-Dist: typer>=0.20.0
Requires-Dist: typing-extensions>=4.15.0; python_version < '3.13'
Requires-Dist: vapoursynth>=69
Requires-Dist: vsjetengine>=1.0.0
Requires-Dist: vspackrgb>=1.0.0
Provides-Extra: essential
Requires-Dist: vsview-frameprops-extended; extra == 'essential'
Requires-Dist: vsview-split-planes; extra == 'essential'
